nsw_fuel/__init__.py
nsw_fuel/client.py
nsw_fuel/dto.py
nsw_fuel_api_client-1.1.3.dist-info/LICENSE
nsw_fuel_api_client-1.1.3.dist-info/METADATA
nsw_fuel_api_client-1.1.3.dist-info/WHEEL
nsw_fuel_api_client-1.1.3.dist-info/top_level.txt
nsw_fuel_api_client-1.1.3.dist-info/RECORD
