Metadata-Version: 2.1
Name: nsw-fuel-api-client
Version: 1.1.3
Summary: API Client for NSW Government Fuel
Home-page: https://github.com/nickw444/nsw-fuel-api-client
Author: Nick Whyte
Author-email: nick@nickwhyte.com
License: UNKNOWN
Platform: UNKNOWN
Classifier: Intended Audience :: Developers
Classifier: Programming Language :: Python
License-File: LICENSE
Requires-Dist: requests
